README.rst
qualname.py
setup.py
qualname.egg-info/PKG-INFO
qualname.egg-info/SOURCES.txt
qualname.egg-info/dependency_links.txt
qualname.egg-info/top_level.txt